AUTHORS.rst
CONTRIBUTING.rst
HISTORY.rst
LICENSE
MANIFEST.in
README.rst
setup.cfg
setup.py
docs/Makefile
docs/authors.rst
docs/conf.py
docs/contributing.rst
docs/history.rst
docs/index.rst
docs/installation.rst
docs/make.bat
docs/readme.rst
docs/usage.rst
model_reduction/__init__.py
model_reduction/cli.py
model_reduction/model_reduction.py
model_reduction.egg-info/PKG-INFO
model_reduction.egg-info/SOURCES.txt
model_reduction.egg-info/dependency_links.txt
model_reduction.egg-info/entry_points.txt
model_reduction.egg-info/not-zip-safe
model_reduction.egg-info/requires.txt
model_reduction.egg-info/top_level.txt
tests/__init__.py
tests/test_model_reduction.py