Metadata-Version: 1.2
Name: model-reduction
Version: 0.1.0
Summary: A Python package to aggregate and reduce water distribution network models
Home-page: https://github.com/meghnathomas/model_reduction
Author: Meghna Sarah Thomas
Author-email: meghnathomas@utexas.edu
License: MIT license
Keywords: model_reduction
Platform: UNKNOWN
Classifier: Development Status :: 2 - Pre-Alpha
Classifier: Intended Audience :: Developers
Classifier: License :: OSI Approved :: MIT License
Classifier: Natural Language :: English
Classifier: Programming Language :: Python :: 3
Classifier: Programming Language :: Python :: 3.5
Classifier: Programming Language :: Python :: 3.6
Classifier: Programming Language :: Python :: 3.7
Classifier: Programming Language :: Python :: 3.8
Requires-Python: >=3.5
